AyDictionary/__init__.py
AyDictionary/core.py
AyDictionary/script.py
AyDictionary/test.py
AyDictionary/test_aydictionary.py
AyDictionary/utils.py
AyDictionary-0.0.4.dist-info/LICENSE
AyDictionary-0.0.4.dist-info/METADATA
AyDictionary-0.0.4.dist-info/WHEEL
AyDictionary-0.0.4.dist-info/top_level.txt
AyDictionary-0.0.4.dist-info/RECORD
