Metadata-Version: 2.1
Name: AyDictionary
Version: 0.0.4
Summary: A dictionary module for Python (Modification of PyDictionary)
Home-page: https://github.com/A91y/AyDictionary
Author: A91y
Author-email: ayush.agr254@gmail.com
License: Copyright (c) 2023 Ayush Agrawal
Project-URL: Bug Tracker, https://github.com/A91y/AyDictionary/issues
Project-URL: Repository, https://github.com/A91y/AyDictionary
Classifier: License :: OSI Approved :: MIT License
Classifier: Operating System :: OS Independent
Classifier: Programming Language :: Python :: Implementation :: CPython
Requires-Python: >=3.6
License-File: LICENSE
Requires-Dist: bs4 (==0.0.1)
Requires-Dist: click
Requires-Dist: requests
